metrics_computation_engine/__init__.py
metrics_computation_engine/cli.py
metrics_computation_engine/constants.py
metrics_computation_engine/dal_cli.py
metrics_computation_engine/logger.py
metrics_computation_engine/main.py
metrics_computation_engine/model_handler.py
metrics_computation_engine/processor.py
metrics_computation_engine/registry.py
metrics_computation_engine/server.py
metrics_computation_engine/types.py
metrics_computation_engine/util.py
metrics_computation_engine/dal/__init__.py
metrics_computation_engine/dal/api_client.py
metrics_computation_engine/dal/utils.py
metrics_computation_engine/entities/README.md
metrics_computation_engine/entities/__init__.py
metrics_computation_engine/entities/types.py
metrics_computation_engine/entities/core/__init__.py
metrics_computation_engine/entities/core/agent_role_detector.py
metrics_computation_engine/entities/core/data_parser.py
metrics_computation_engine/entities/core/session_aggregator.py
metrics_computation_engine/entities/core/trace_processor.py
metrics_computation_engine/entities/models/__init__.py
metrics_computation_engine/entities/models/api_metric.py
metrics_computation_engine/entities/models/conversation_utils.py
metrics_computation_engine/entities/models/enhanced_agent_view.py
metrics_computation_engine/entities/models/execution_tree.py
metrics_computation_engine/entities/models/session.py
metrics_computation_engine/entities/models/session_set.py
metrics_computation_engine/entities/models/session_set_printer.py
metrics_computation_engine/entities/models/span.py
metrics_computation_engine/entities/transformers/__init__.py
metrics_computation_engine/entities/transformers/base.py
metrics_computation_engine/entities/transformers/core.py
metrics_computation_engine/entities/transformers/execution_tree_transformer.py
metrics_computation_engine/entities/transformers/session_enrichers.py
metrics_computation_engine/examples/README.md
metrics_computation_engine/examples/mce-demo.py
metrics_computation_engine-1.2.7.dist-info/METADATA
metrics_computation_engine-1.2.7.dist-info/WHEEL
metrics_computation_engine-1.2.7.dist-info/entry_points.txt
metrics_computation_engine-1.2.7.dist-info/RECORD
