Metadata-Version: 2.4
Name: metrics-computation-engine
Version: 1.2.7
Summary: Service for computing metrics on AI agent performance data
Project-URL: Homepage, https://github.com/agntcy/telemetry-hub
Project-URL: Repository, https://github.com/agntcy/telemetry-hub
Project-URL: Issues, https://github.com/agntcy/telemetry-hub/issues
Author: Agntcy Telemetry Hub Team
License-Expression: Apache-2.0
Classifier: Development Status :: 3 - Alpha
Classifier: Intended Audience :: Developers
Classifier: Programming Language :: Python :: 3
Classifier: Programming Language :: Python :: 3.10
Classifier: Programming Language :: Python :: 3.11
Classifier: Programming Language :: Python :: 3.12
Requires-Python: >=3.11
Requires-Dist: apscheduler>=3.10.0
Requires-Dist: click>=8.0.0
Requires-Dist: cryptography>=3.0.0
Requires-Dist: fastapi>=0.100.0
Requires-Dist: langchain-core>=0.3.69
Requires-Dist: litellm>=1.0.0
Requires-Dist: networkx>=3.0.0
Requires-Dist: pandas>=1.5.0
Requires-Dist: pydantic-settings>=2.10.1
Requires-Dist: pydantic>=2.0.0
Requires-Dist: python-dotenv>=1.0.0
Requires-Dist: requests>=2.28.0
Requires-Dist: uvicorn[standard]>=0.20.0
Provides-Extra: adapters
Requires-Dist: mce-deepeval-adapter>=0.1.0; extra == 'adapters'
Requires-Dist: mce-opik-adapter>=0.1.0; extra == 'adapters'
Requires-Dist: mce-ragas-adapter>=0.1.0; extra == 'adapters'
Provides-Extra: all
Requires-Dist: mce-deepeval-adapter>=0.1.0; extra == 'all'
Requires-Dist: mce-metrics-plugin>=0.1.0; extra == 'all'
Requires-Dist: mce-opik-adapter>=0.1.0; extra == 'all'
Requires-Dist: mce-ragas-adapter>=0.1.0; extra == 'all'
Provides-Extra: deepeval
Requires-Dist: mce-deepeval-adapter>=0.1.0; extra == 'deepeval'
Provides-Extra: dev
Requires-Dist: black>=23.0.0; extra == 'dev'
Requires-Dist: flake8>=6.0.0; extra == 'dev'
Requires-Dist: httpx>=0.24.0; extra == 'dev'
Requires-Dist: isort>=5.12.0; extra == 'dev'
Requires-Dist: pytest-asyncio>=0.21.0; extra == 'dev'
Requires-Dist: pytest>=7.0.0; extra == 'dev'
Provides-Extra: metrics-plugin
Requires-Dist: mce-metrics-plugin>=0.1.0; extra == 'metrics-plugin'
Provides-Extra: opik
Requires-Dist: mce-opik-adapter>=0.1.0; extra == 'opik'
Provides-Extra: ragas
Requires-Dist: mce-ragas-adapter>=0.1.0; extra == 'ragas'
Provides-Extra: test
Requires-Dist: httpx>=0.24.0; extra == 'test'
Requires-Dist: pytest-asyncio>=0.21.0; extra == 'test'
Requires-Dist: pytest>=7.0.0; extra == 'test'
